main.py
thcli-1.4.0.dist-info/METADATA
thcli-1.4.0.dist-info/WHEEL
thcli-1.4.0.dist-info/entry_points.txt
thcli-1.4.0.dist-info/top_level.txt
thcli-1.4.0.dist-info/RECORD
