Metadata-Version: 2.1
Name: thcli
Version: 1.4.0
Summary: Greeting for fun.
Author: Taehoon Kang
Author-email: kangthink@gmail.com
Classifier: Programming Language :: Python :: 3
Classifier: License :: OSI Approved :: MIT License
Classifier: Operating System :: OS Independent
Requires-Python: >=3.8
Requires-Dist: emoji (==2.2.0)
